frappe/__init__.py
frappe/database/__init__.py
frappe/database/database.py
frappe/database/db_manager.py
frappe/database/schema.py
frappe/database/mariadb/__init__.py
frappe/database/mariadb/database.py
frappe/database/mariadb/schema.py
frappe/database/mariadb/setup_db.py
frappe/database/postgres/__init__.py
frappe/database/postgres/database.py
frappe/database/postgres/schema.py
frappe/database/postgres/setup_db.py
frappe/defaults/__init__.py
frappe/model/__init__.py
frappe/model/base_document.py
frappe/model/create_new.py
frappe/model/db_query.py
frappe/model/delete_doc.py
frappe/model/docfield.py
frappe/model/document.py
frappe/model/dynamic_links.py
frappe/model/mapper.py
frappe/model/meta.py
frappe/model/naming.py
frappe/model/utils/__init__.py
frappe/model/utils/link_count.py
frappe/model/utils/rename_field.py
frappe/model/utils/user_settings.py
frappe/utils/__init__.py
frappe/utils/background_jobs.py
frappe/utils/file_lock.py
frappe/utils/formatters.py
frappe/utils/nestedset.py
frappe_orm-1.0.0.dist-info/METADATA
frappe_orm-1.0.0.dist-info/WHEEL
frappe_orm-1.0.0.dist-info/top_level.txt
frappe_orm-1.0.0.dist-info/RECORD
