Metadata-Version: 2.1
Name: frappe-orm
Version: 1.0.0
Summary: Frappe Framework Orm
Home-page: UNKNOWN
Author: omar hamdy
Author-email: omarhamdy49@gmail.com
License: MIT
Keywords: frappe,orm,postgres,mariadb,database
Platform: UNKNOWN
